project_paths/__init__.py
project_paths/py.typed
project_paths-1.1.1.dist-info/LICENSE
project_paths-1.1.1.dist-info/WHEEL
project_paths-1.1.1.dist-info/METADATA
project_paths-1.1.1.dist-info/RECORD
