Metadata-Version: 2.1
Name: project-paths
Version: 1.1.1
Summary: Access file paths from pyproject.toml
Home-page: https://github.com/eddieantonio/project-paths
License: MIT
Keywords: pathlib,pyproject.toml,paths,configuration
Author: Eddie Antonio Santos
Author-email: eddieantonio@hey.com
Requires-Python: >=3.8,<4.0
Classifier: Development Status :: 5 - Production/Stable
Classifier: Intended Audience :: Developers
Classifier: License :: OSI Approved :: MIT License
Classifier: Programming Language :: Python :: 3
Classifier: Programming Language :: Python :: 3.8
Classifier: Programming Language :: Python :: 3.9
Classifier: Topic :: Software Development :: Libraries :: Python Modules
Requires-Dist: toml (>=0.10.2,<0.11.0)
Project-URL: Repository, https://github.com/eddieantonio/project-paths
